azure/mgmt/hybridcontainerservice/__init__.py
azure/mgmt/hybridcontainerservice/_configuration.py
azure/mgmt/hybridcontainerservice/_hybrid_container_service_mgmt_client.py
azure/mgmt/hybridcontainerservice/_patch.py
azure/mgmt/hybridcontainerservice/_serialization.py
azure/mgmt/hybridcontainerservice/_vendor.py
azure/mgmt/hybridcontainerservice/_version.py
azure/mgmt/hybridcontainerservice/py.typed
azure/mgmt/hybridcontainerservice/aio/__init__.py
azure/mgmt/hybridcontainerservice/aio/_configuration.py
azure/mgmt/hybridcontainerservice/aio/_hybrid_container_service_mgmt_client.py
azure/mgmt/hybridcontainerservice/aio/_patch.py
azure/mgmt/hybridcontainerservice/aio/_vendor.py
azure/mgmt/hybridcontainerservice/aio/operations/__init__.py
azure/mgmt/hybridcontainerservice/aio/operations/_agent_pool_operations.py
azure/mgmt/hybridcontainerservice/aio/operations/_hybrid_container_service_mgmt_client_operations.py
azure/mgmt/hybridcontainerservice/aio/operations/_hybrid_identity_metadata_operations.py
azure/mgmt/hybridcontainerservice/aio/operations/_kubernetes_versions_operations.py
azure/mgmt/hybridcontainerservice/aio/operations/_operations.py
azure/mgmt/hybridcontainerservice/aio/operations/_patch.py
azure/mgmt/hybridcontainerservice/aio/operations/_provisioned_cluster_instances_operations.py
azure/mgmt/hybridcontainerservice/aio/operations/_virtual_networks_operations.py
azure/mgmt/hybridcontainerservice/aio/operations/_vm_skus_operations.py
azure/mgmt/hybridcontainerservice/models/__init__.py
azure/mgmt/hybridcontainerservice/models/_hybrid_container_service_mgmt_client_enums.py
azure/mgmt/hybridcontainerservice/models/_models_py3.py
azure/mgmt/hybridcontainerservice/models/_patch.py
azure/mgmt/hybridcontainerservice/operations/__init__.py
azure/mgmt/hybridcontainerservice/operations/_agent_pool_operations.py
azure/mgmt/hybridcontainerservice/operations/_hybrid_container_service_mgmt_client_operations.py
azure_mgmt_hybridcontainerservice-1.0.0.dist-info/LICENSE
azure_mgmt_hybridcontainerservice-1.0.0.dist-info/METADATA
azure_mgmt_hybridcontainerservice-1.0.0.dist-info/WHEEL
azure_mgmt_hybridcontainerservice-1.0.0.dist-info/top_level.txt
azure_mgmt_hybridcontainerservice-1.0.0.dist-info/RECORD
